{
  "round": "round_2",
  "epochs": [
    {
      "epoch": "final",
      "timestamp": "2026-04-28T17:32:48.759365",
      "global_norm": 0.0,
      "trainable_params": 0,
      "frozen_params": 0,
      "layer_summary": [
        {
          "name": "first_conv.conv.weight",
          "mean": -0.0003997042076662183,
          "std": 0.07613243907690048
        },
        {
          "name": "first_conv.conv.bias",
          "mean": 0.06002608686685562,
          "std": 0.10862716287374496
        },
        {
          "name": "first_bn.weight",
          "mean": 1.0,
          "std": 0.0
        },
        {
          "name": "first_bn.bias",
          "mean": 0.0,
          "std": 0.0
        },
        {
          "name": "first_bn.running_mean",
          "mean": 0.0,
          "std": 0.0
        },
        {
          "name": "first_bn.running_var",
          "mean": 1.0,
          "std": 0.0
        },
        {
          "name": "stage_list.0.block_list.0.bn1.weight",
          "mean": 1.0,
          "std": 0.0
        },
        {
          "name": "stage_list.0.block_list.0.bn1.bias",
          "mean": 0.0,
          "std": 0.0
        },
        {
          "name": "stage_list.0.block_list.0.bn1.running_mean",
          "mean": 0.0,
          "std": 0.0
        },
        {
          "name": "stage_list.0.block_list.0.bn1.running_var",
          "mean": 1.0,
          "std": 0.0
        },
        {
          "name": "stage_list.0.block_list.0.conv1.conv.weight",
          "mean": -0.032773084938526154,
          "std": 0.13412685692310333
        },
        {
          "name": "stage_list.0.block_list.0.conv1.conv.bias",
          "mean": 0.04465174674987793,
          "std": 0.13158628344535828
        },
        {
          "name": "stage_list.0.block_list.0.bn2.weight",
          "mean": 1.0,
          "std": 0.0
        },
        {
          "name": "stage_list.0.block_list.0.bn2.bias",
          "mean": 0.0,
          "std": 0.0
        },
        {
          "name": "stage_list.0.block_list.0.bn2.running_mean",
          "mean": 0.0,
          "std": 0.0
        },
        {
          "name": "stage_list.0.block_list.0.bn2.running_var",
          "mean": 1.0,
          "std": 0.0
        },
        {
          "name": "stage_list.0.block_list.0.conv2.conv.weight",
          "mean": -0.015035813674330711,
          "std": 0.11009183526039124
        },
        {
          "name": "stage_list.0.block_list.0.conv2.conv.bias",
          "mean": 0.04526156187057495,
          "std": 0.05894770845770836
        },
        {
          "name": "stage_list.0.block_list.0.bn3.weight",
          "mean": 1.0,
          "std": 0.0
        },
        {
          "name": "stage_list.0.block_list.0.bn3.bias",
          "mean": 0.0,
          "std": 0.0
        },
        {
          "name": "stage_list.0.block_list.0.bn3.running_mean",
          "mean": 0.0,
          "std": 0.0
        },
        {
          "name": "stage_list.0.block_list.0.bn3.running_var",
          "mean": 1.0,
          "std": 0.0
        },
        {
          "name": "stage_list.0.block_list.0.conv3.conv.weight",
          "mean": -0.017086733132600784,
          "std": 0.12555693089962006
        },
        {
          "name": "stage_list.0.block_list.0.conv3.conv.bias",
          "mean": -0.06364640593528748,
          "std": 0.09448486566543579
        },
        {
          "name": "stage_list.0.block_list.0.se_fc1.weight",
          "mean": 0.03274459019303322,
          "std": 0.13569168746471405
        },
        {
          "name": "stage_list.0.block_list.0.se_fc1.bias",
          "mean": -0.023385485634207726,
          "std": 0.15409299731254578
        },
        {
          "name": "stage_list.0.block_list.0.se_fc2.weight",
          "mean": -0.035180430859327316,
          "std": 0.16157306730747223
        },
        {
          "name": "stage_list.0.block_list.0.se_fc2.bias",
          "mean": 0.06805016100406647,
          "std": 0.12878455221652985
        },
        {
          "name": "stage_list.0.block_list.1.bn1.weight",
          "mean": 1.0,
          "std": 0.0
        },
        {
          "name": "stage_list.0.block_list.1.bn1.bias",
          "mean": 0.0,
          "std": 0.0
        },
        {
          "name": "stage_list.0.block_list.1.bn1.running_mean",
          "mean": 0.0,
          "std": 0.0
        },
        {
          "name": "stage_list.0.block_list.1.bn1.running_var",
          "mean": 1.0,
          "std": 0.0
        },
        {
          "name": "stage_list.0.block_list.1.conv1.conv.weight",
          "mean": -0.028708161786198616,
          "std": 0.13064730167388916
        },
        {
          "name": "stage_list.0.block_list.1.conv1.conv.bias",
          "mean": -0.011047963984310627,
          "std": 0.10867423564195633
        },
        {
          "name": "stage_list.0.block_list.1.bn2.weight",
          "mean": 1.0,
          "std": 0.0
        },
        {
          "name": "stage_list.0.block_list.1.bn2.bias",
          "mean": 0.0,
          "std": 0.0
        },
        {
          "name": "stage_list.0.block_list.1.bn2.running_mean",
          "mean": 0.0,
          "std": 0.0
        },
        {
          "name": "stage_list.0.block_list.1.bn2.running_var",
          "mean": 1.0,
          "std": 0.0
        },
        {
          "name": "stage_list.0.block_list.1.conv2.conv.weight",
          "mean": -0.010494677349925041,
          "std": 0.09848728030920029
        },
        {
          "name": "stage_list.0.block_list.1.conv2.conv.bias",
          "mean": -0.01569538377225399,
          "std": 0.0760754719376564
        },
        {
          "name": "stage_list.0.block_list.1.bn3.weight",
          "mean": 1.0,
          "std": 0.0
        },
        {
          "name": "stage_list.0.block_list.1.bn3.bias",
          "mean": 0.0,
          "std": 0.0
        },
        {
          "name": "stage_list.0.block_list.1.bn3.running_mean",
          "mean": 0.0,
          "std": 0.0
        },
        {
          "name": "stage_list.0.block_list.1.bn3.running_var",
          "mean": 1.0,
          "std": 0.0
        },
        {
          "name": "stage_list.0.block_list.1.conv3.conv.weight",
          "mean": -0.01366032101213932,
          "std": 0.10954422503709793
        },
        {
          "name": "stage_list.0.block_list.1.conv3.conv.bias",
          "mean": -0.06403658539056778,
          "std": 0.07886145263910294
        },
        {
          "name": "stage_list.0.block_list.1.se_fc1.weight",
          "mean": 0.009453103877604008,
          "std": 0.1335911899805069
        },
        {
          "name": "stage_list.0.block_list.1.se_fc1.bias",
          "mean": 0.01514887623488903,
          "std": 0.09791042655706406
        },
        {
          "name": "stage_list.0.block_list.1.se_fc2.weight",
          "mean": 0.009703309275209904,
          "std": 0.14947912096977234
        },
        {
          "name": "stage_list.0.block_list.1.se_fc2.bias",
          "mean": -0.02788262628018856,
          "std": 0.14631053805351257
        },
        {
          "name": "stage_list.1.block_list.0.bn1.weight",
          "mean": 1.0,
          "std": 0.0
        },
        {
          "name": "stage_list.1.block_list.0.bn1.bias",
          "mean": 0.0,
          "std": 0.0
        },
        {
          "name": "stage_list.1.block_list.0.bn1.running_mean",
          "mean": 0.0,
          "std": 0.0
        },
        {
          "name": "stage_list.1.block_list.0.bn1.running_var",
          "mean": 1.0,
          "std": 0.0
        },
        {
          "name": "stage_list.1.block_list.0.conv1.conv.weight",
          "mean": -0.02814050018787384,
          "std": 0.13044828176498413
        },
        {
          "name": "stage_list.1.block_list.0.conv1.conv.bias",
          "mean": -0.016347061842679977,
          "std": 0.07762167602777481
        },
        {
          "name": "stage_list.1.block_list.0.bn2.weight",
          "mean": 1.0,
          "std": 0.0
        },
        {
          "name": "stage_list.1.block_list.0.bn2.bias",
          "mean": 0.0,
          "std": 0.0
        },
        {
          "name": "stage_list.1.block_list.0.bn2.running_mean",
          "mean": 0.0,
          "std": 0.0
        },
        {
          "name": "stage_list.1.block_list.0.bn2.running_var",
          "mean": 1.0,
          "std": 0.0
        },
        {
          "name": "stage_list.1.block_list.0.conv2.conv.weight",
          "mean": -0.01098571252077818,
          "std": 0.09917939454317093
        },
        {
          "name": "stage_list.1.block_list.0.conv2.conv.bias",
          "mean": -0.03023054264485836,
          "std": 0.05188145488500595
        },
        {
          "name": "stage_list.1.block_list.0.bn3.weight",
          "mean": 1.0,
          "std": 0.0
        },
        {
          "name": "stage_list.1.block_list.0.bn3.bias",
          "mean": 0.0,
          "std": 0.0
        },
        {
          "name": "stage_list.1.block_list.0.bn3.running_mean",
          "mean": 0.0,
          "std": 0.0
        },
        {
          "name": "stage_list.1.block_list.0.bn3.running_var",
          "mean": 1.0,
          "std": 0.0
        },
        {
          "name": "stage_list.1.block_list.0.conv3.conv.weight",
          "mean": -0.013789084739983082,
          "std": 0.0975341871380806
        },
        {
          "name": "stage_list.1.block_list.0.conv3.conv.bias",
          "mean": -0.02374727465212345,
          "std": 0.06882550567388535
        },
        {
          "name": "stage_list.1.block_list.0.se_fc1.weight",
          "mean": 0.03125660866498947,
          "std": 0.1063971146941185
        },
        {
          "name": "stage_list.1.block_list.0.se_fc1.bias",
          "mean": -0.010897192172706127,
          "std": 0.08750846236944199
        },
        {
          "name": "stage_list.1.block_list.0.se_fc2.weight",
          "mean": 0.0015391323249787092,
          "std": 0.11851104348897934
        },
        {
          "name": "stage_list.1.block_list.0.se_fc2.bias",
          "mean": -0.019095171242952347,
          "std": 0.1084979698061943
        },
        {
          "name": "stage_list.1.block_list.1.bn1.weight",
          "mean": 1.0,
          "std": 0.0
        },
        {
          "name": "stage_list.1.block_list.1.bn1.bias",
          "mean": 0.0,
          "std": 0.0
        },
        {
          "name": "stage_list.1.block_list.1.bn1.running_mean",
          "mean": 0.0,
          "std": 0.0
        },
        {
          "name": "stage_list.1.block_list.1.bn1.running_var",
          "mean": 1.0,
          "std": 0.0
        },
        {
          "name": "stage_list.1.block_list.1.conv1.conv.weight",
          "mean": -0.013785939663648605,
          "std": 0.11322606354951859
        },
        {
          "name": "stage_list.1.block_list.1.conv1.conv.bias",
          "mean": 0.008918454870581627,
          "std": 0.07534842193126678
        },
        {
          "name": "stage_list.1.block_list.1.bn2.weight",
          "mean": 1.0,
          "std": 0.0
        },
        {
          "name": "stage_list.1.block_list.1.bn2.bias",
          "mean": 0.0,
          "std": 0.0
        },
        {
          "name": "stage_list.1.block_list.1.bn2.running_mean",
          "mean": 0.0,
          "std": 0.0
        },
        {
          "name": "stage_list.1.block_list.1.bn2.running_var",
          "mean": 1.0,
          "std": 0.0
        },
        {
          "name": "stage_list.1.block_list.1.conv2.conv.weight",
          "mean": -0.009619593620300293,
          "std": 0.10236828774213791
        },
        {
          "name": "stage_list.1.block_list.1.conv2.conv.bias",
          "mean": -0.03549633175134659,
          "std": 0.06295434385538101
        },
        {
          "name": "stage_list.1.block_list.1.bn3.weight",
          "mean": 1.0,
          "std": 0.0
        },
        {
          "name": "stage_list.1.block_list.1.bn3.bias",
          "mean": 0.0,
          "std": 0.0
        },
        {
          "name": "stage_list.1.block_list.1.bn3.running_mean",
          "mean": 0.0,
          "std": 0.0
        },
        {
          "name": "stage_list.1.block_list.1.bn3.running_var",
          "mean": 1.0,
          "std": 0.0
        },
        {
          "name": "stage_list.1.block_list.1.conv3.conv.weight",
          "mean": -0.009705525822937489,
          "std": 0.09912560135126114
        },
        {
          "name": "stage_list.1.block_list.1.conv3.conv.bias",
          "mean": -0.05652330070734024,
          "std": 0.06837702542543411
        },
        {
          "name": "stage_list.1.block_list.1.se_fc1.weight",
          "mean": 0.01666867360472679,
          "std": 0.1022203266620636
        },
        {
          "name": "stage_list.1.block_list.1.se_fc1.bias",
          "mean": 0.018700746819376945,
          "std": 0.09110768884420395
        },
        {
          "name": "stage_list.1.block_list.1.se_fc2.weight",
          "mean": 0.007508334703743458,
          "std": 0.11959666013717651
        },
        {
          "name": "stage_list.1.block_list.1.se_fc2.bias",
          "mean": 0.0023667269852012396,
          "std": 0.124024398624897
        },
        {
          "name": "stage_list.2.block_list.0.bn1.weight",
          "mean": 1.0,
          "std": 0.0
        },
        {
          "name": "stage_list.2.block_list.0.bn1.bias",
          "mean": 0.0,
          "std": 0.0
        },
        {
          "name": "stage_list.2.block_list.0.bn1.running_mean",
          "mean": 0.0,
          "std": 0.0
        },
        {
          "name": "stage_list.2.block_list.0.bn1.running_var",
          "mean": 1.0,
          "std": 0.0
        },
        {
          "name": "stage_list.2.block_list.0.conv1.conv.weight",
          "mean": -0.011047108098864555,
          "std": 0.10986145585775375
        },
        {
          "name": "stage_list.2.block_list.0.conv1.conv.bias",
          "mean": -0.027230342850089073,
          "std": 0.050305940210819244
        },
        {
          "name": "stage_list.2.block_list.0.bn2.weight",
          "mean": 1.0,
          "std": 0.0
        },
        {
          "name": "stage_list.2.block_list.0.bn2.bias",
          "mean": 0.0,
          "std": 0.0
        },
        {
          "name": "stage_list.2.block_list.0.bn2.running_mean",
          "mean": 0.0,
          "std": 0.0
        },
        {
          "name": "stage_list.2.block_list.0.bn2.running_var",
          "mean": 1.0,
          "std": 0.0
        },
        {
          "name": "stage_list.2.block_list.0.conv2.conv.weight",
          "mean": -0.011478041298687458,
          "std": 0.09985054284334183
        },
        {
          "name": "stage_list.2.block_list.0.conv2.conv.bias",
          "mean": -0.0203627310693264,
          "std": 0.06477630883455276
        },
        {
          "name": "stage_list.2.block_list.0.bn3.weight",
          "mean": 1.0,
          "std": 0.0
        },
        {
          "name": "stage_list.2.block_list.0.bn3.bias",
          "mean": 0.0,
          "std": 0.0
        },
        {
          "name": "stage_list.2.block_list.0.bn3.running_mean",
          "mean": 0.0,
          "std": 0.0
        },
        {
          "name": "stage_list.2.block_list.0.bn3.running_var",
          "mean": 1.0,
          "std": 0.0
        },
        {
          "name": "stage_list.2.block_list.0.conv3.conv.weight",
          "mean": -0.010831606574356556,
          "std": 0.09473919868469238
        },
        {
          "name": "stage_list.2.block_list.0.conv3.conv.bias",
          "mean": -0.05792152136564255,
          "std": 0.06427370011806488
        },
        {
          "name": "stage_list.2.block_list.0.se_fc1.weight",
          "mean": 0.02285081148147583,
          "std": 0.08852138370275497
        },
        {
          "name": "stage_list.2.block_list.0.se_fc1.bias",
          "mean": -0.02313397265970707,
          "std": 0.09419561177492142
        },
        {
          "name": "stage_list.2.block_list.0.se_fc2.weight",
          "mean": 0.01379683893173933,
          "std": 0.11162891238927841
        },
        {
          "name": "stage_list.2.block_list.0.se_fc2.bias",
          "mean": -0.035130079835653305,
          "std": 0.11452944576740265
        },
        {
          "name": "stage_list.2.block_list.1.bn1.weight",
          "mean": 1.0,
          "std": 0.0
        },
        {
          "name": "stage_list.2.block_list.1.bn1.bias",
          "mean": 0.0,
          "std": 0.0
        },
        {
          "name": "stage_list.2.block_list.1.bn1.running_mean",
          "mean": 0.0,
          "std": 0.0
        },
        {
          "name": "stage_list.2.block_list.1.bn1.running_var",
          "mean": 1.0,
          "std": 0.0
        },
        {
          "name": "stage_list.2.block_list.1.conv1.conv.weight",
          "mean": -0.019040463492274284,
          "std": 0.10779939591884613
        },
        {
          "name": "stage_list.2.block_list.1.conv1.conv.bias",
          "mean": -0.002201701048761606,
          "std": 0.06789002567529678
        },
        {
          "name": "stage_list.2.block_list.1.bn2.weight",
          "mean": 1.0,
          "std": 0.0
        },
        {
          "name": "stage_list.2.block_list.1.bn2.bias",
          "mean": 0.0,
          "std": 0.0
        },
        {
          "name": "stage_list.2.block_list.1.bn2.running_mean",
          "mean": 0.0,
          "std": 0.0
        },
        {
          "name": "stage_list.2.block_list.1.bn2.running_var",
          "mean": 1.0,
          "std": 0.0
        },
        {
          "name": "stage_list.2.block_list.1.conv2.conv.weight",
          "mean": -0.010550717823207378,
          "std": 0.09596234560012817
        },
        {
          "name": "stage_list.2.block_list.1.conv2.conv.bias",
          "mean": -0.03619663789868355,
          "std": 0.06154564395546913
        },
        {
          "name": "stage_list.2.block_list.1.bn3.weight",
          "mean": 1.0,
          "std": 0.0
        },
        {
          "name": "stage_list.2.block_list.1.bn3.bias",
          "mean": 0.0,
          "std": 0.0
        },
        {
          "name": "stage_list.2.block_list.1.bn3.running_mean",
          "mean": 0.0,
          "std": 0.0
        },
        {
          "name": "stage_list.2.block_list.1.bn3.running_var",
          "mean": 1.0,
          "std": 0.0
        },
        {
          "name": "stage_list.2.block_list.1.conv3.conv.weight",
          "mean": -0.006756059359759092,
          "std": 0.09219510108232498
        },
        {
          "name": "stage_list.2.block_list.1.conv3.conv.bias",
          "mean": -0.048272594809532166,
          "std": 0.06459139287471771
        },
        {
          "name": "stage_list.2.block_list.1.se_fc1.weight",
          "mean": 0.026399124413728714,
          "std": 0.10349500179290771
        },
        {
          "name": "stage_list.2.block_list.1.se_fc1.bias",
          "mean": -0.01876709796488285,
          "std": 0.0956493690609932
        },
        {
          "name": "stage_list.2.block_list.1.se_fc2.weight",
          "mean": 0.010582197457551956,
          "std": 0.11864162236452103
        },
        {
          "name": "stage_list.2.block_list.1.se_fc2.bias",
          "mean": -0.055264364928007126,
          "std": 0.09369135648012161
        },
        {
          "name": "stage_list.3.block_list.0.bn1.weight",
          "mean": 1.0,
          "std": 0.0
        },
        {
          "name": "stage_list.3.block_list.0.bn1.bias",
          "mean": 0.0,
          "std": 0.0
        },
        {
          "name": "stage_list.3.block_list.0.bn1.running_mean",
          "mean": 0.0,
          "std": 0.0
        },
        {
          "name": "stage_list.3.block_list.0.bn1.running_var",
          "mean": 1.0,
          "std": 0.0
        },
        {
          "name": "stage_list.3.block_list.0.conv1.conv.weight",
          "mean": -0.014459295198321342,
          "std": 0.1022372916340828
        },
        {
          "name": "stage_list.3.block_list.0.conv1.conv.bias",
          "mean": -0.02437385730445385,
          "std": 0.0654572993516922
        },
        {
          "name": "stage_list.3.block_list.0.bn2.weight",
          "mean": 1.0,
          "std": 0.0
        },
        {
          "name": "stage_list.3.block_list.0.bn2.bias",
          "mean": 0.0,
          "std": 0.0
        },
        {
          "name": "stage_list.3.block_list.0.bn2.running_mean",
          "mean": 0.0,
          "std": 0.0
        },
        {
          "name": "stage_list.3.block_list.0.bn2.running_var",
          "mean": 1.0,
          "std": 0.0
        },
        {
          "name": "stage_list.3.block_list.0.conv2.conv.weight",
          "mean": -0.00517153600230813,
          "std": 0.08993908762931824
        },
        {
          "name": "stage_list.3.block_list.0.conv2.conv.bias",
          "mean": -0.03810429945588112,
          "std": 0.059645045548677444
        },
        {
          "name": "stage_list.3.block_list.0.bn3.weight",
          "mean": 1.0,
          "std": 0.0
        },
        {
          "name": "stage_list.3.block_list.0.bn3.bias",
          "mean": 0.0,
          "std": 0.0
        },
        {
          "name": "stage_list.3.block_list.0.bn3.running_mean",
          "mean": 0.0,
          "std": 0.0
        },
        {
          "name": "stage_list.3.block_list.0.bn3.running_var",
          "mean": 1.0,
          "std": 0.0
        },
        {
          "name": "stage_list.3.block_list.0.conv3.conv.weight",
          "mean": -0.005026702303439379,
          "std": 0.0808785930275917
        },
        {
          "name": "stage_list.3.block_list.0.conv3.conv.bias",
          "mean": -0.04198838770389557,
          "std": 0.05782874673604965
        },
        {
          "name": "stage_list.3.block_list.0.se_fc1.weight",
          "mean": 0.024046190083026886,
          "std": 0.06950446218252182
        },
        {
          "name": "stage_list.3.block_list.0.se_fc1.bias",
          "mean": -0.02169487066566944,
          "std": 0.05582118406891823
        },
        {
          "name": "stage_list.3.block_list.0.se_fc2.weight",
          "mean": 0.017479130998253822,
          "std": 0.0906643345952034
        },
        {
          "name": "stage_list.3.block_list.0.se_fc2.bias",
          "mean": -0.06858532130718231,
          "std": 0.10241346806287766
        },
        {
          "name": "stage_list.3.block_list.1.bn1.weight",
          "mean": 1.0,
          "std": 0.0
        },
        {
          "name": "stage_list.3.block_list.1.bn1.bias",
          "mean": 0.0,
          "std": 0.0
        },
        {
          "name": "stage_list.3.block_list.1.bn1.running_mean",
          "mean": 0.0,
          "std": 0.0
        },
        {
          "name": "stage_list.3.block_list.1.bn1.running_var",
          "mean": 1.0,
          "std": 0.0
        },
        {
          "name": "stage_list.3.block_list.1.conv1.conv.weight",
          "mean": -0.004713680129498243,
          "std": 0.08719341456890106
        },
        {
          "name": "stage_list.3.block_list.1.conv1.conv.bias",
          "mean": -0.00994617585092783,
          "std": 0.05899031460285187
        },
        {
          "name": "stage_list.3.block_list.1.bn2.weight",
          "mean": 1.0,
          "std": 0.0
        },
        {
          "name": "stage_list.3.block_list.1.bn2.bias",
          "mean": 0.0,
          "std": 0.0
        },
        {
          "name": "stage_list.3.block_list.1.bn2.running_mean",
          "mean": 0.0,
          "std": 0.0
        },
        {
          "name": "stage_list.3.block_list.1.bn2.running_var",
          "mean": 1.0,
          "std": 0.0
        },
        {
          "name": "stage_list.3.block_list.1.conv2.conv.weight",
          "mean": -0.002497181063517928,
          "std": 0.08450397849082947
        },
        {
          "name": "stage_list.3.block_list.1.conv2.conv.bias",
          "mean": -0.045357074588537216,
          "std": 0.05201147869229317
        },
        {
          "name": "stage_list.3.block_list.1.bn3.weight",
          "mean": 1.0,
          "std": 0.0
        },
        {
          "name": "stage_list.3.block_list.1.bn3.bias",
          "mean": 0.0,
          "std": 0.0
        },
        {
          "name": "stage_list.3.block_list.1.bn3.running_mean",
          "mean": 0.0,
          "std": 0.0
        },
        {
          "name": "stage_list.3.block_list.1.bn3.running_var",
          "mean": 1.0,
          "std": 0.0
        },
        {
          "name": "stage_list.3.block_list.1.conv3.conv.weight",
          "mean": -0.0037616961635649204,
          "std": 0.07828803360462189
        },
        {
          "name": "stage_list.3.block_list.1.conv3.conv.bias",
          "mean": -0.041737861931324005,
          "std": 0.053261011838912964
        },
        {
          "name": "stage_list.3.block_list.1.se_fc1.weight",
          "mean": 0.02690330147743225,
          "std": 0.0658324807882309
        },
        {
          "name": "stage_list.3.block_list.1.se_fc1.bias",
          "mean": -0.03704000636935234,
          "std": 0.06356057524681091
        },
        {
          "name": "stage_list.3.block_list.1.se_fc2.weight",
          "mean": 0.02241971343755722,
          "std": 0.08479196578264236
        },
        {
          "name": "stage_list.3.block_list.1.se_fc2.bias",
          "mean": -0.08462923765182495,
          "std": 0.0716937705874443
        },
        {
          "name": "stage_list.3.block_list.2.bn1.weight",
          "mean": 1.0,
          "std": 0.0
        },
        {
          "name": "stage_list.3.block_list.2.bn1.bias",
          "mean": 0.0,
          "std": 0.0
        },
        {
          "name": "stage_list.3.block_list.2.bn1.running_mean",
          "mean": 0.0,
          "std": 0.0
        },
        {
          "name": "stage_list.3.block_list.2.bn1.running_var",
          "mean": 1.0,
          "std": 0.0
        },
        {
          "name": "stage_list.3.block_list.2.conv1.conv.weight",
          "mean": -0.002529220888391137,
          "std": 0.08951792120933533
        },
        {
          "name": "stage_list.3.block_list.2.conv1.conv.bias",
          "mean": -0.02478417381644249,
          "std": 0.05995455011725426
        },
        {
          "name": "stage_list.3.block_list.2.bn2.weight",
          "mean": 1.0,
          "std": 0.0
        },
        {
          "name": "stage_list.3.block_list.2.bn2.bias",
          "mean": 0.0,
          "std": 0.0
        },
        {
          "name": "stage_list.3.block_list.2.bn2.running_mean",
          "mean": 0.0,
          "std": 0.0
        },
        {
          "name": "stage_list.3.block_list.2.bn2.running_var",
          "mean": 1.0,
          "std": 0.0
        },
        {
          "name": "stage_list.3.block_list.2.conv2.conv.weight",
          "mean": -0.0044418154284358025,
          "std": 0.09095604717731476
        },
        {
          "name": "stage_list.3.block_list.2.conv2.conv.bias",
          "mean": -0.042874064296483994,
          "std": 0.06328663975000381
        },
        {
          "name": "stage_list.3.block_list.2.bn3.weight",
          "mean": 1.0,
          "std": 0.0
        },
        {
          "name": "stage_list.3.block_list.2.bn3.bias",
          "mean": 0.0,
          "std": 0.0
        },
        {
          "name": "stage_list.3.block_list.2.bn3.running_mean",
          "mean": 0.0,
          "std": 0.0
        },
        {
          "name": "stage_list.3.block_list.2.bn3.running_var",
          "mean": 1.0,
          "std": 0.0
        },
        {
          "name": "stage_list.3.block_list.2.conv3.conv.weight",
          "mean": -0.005326328799128532,
          "std": 0.08183671534061432
        },
        {
          "name": "stage_list.3.block_list.2.conv3.conv.bias",
          "mean": -0.03318972885608673,
          "std": 0.047391410917043686
        },
        {
          "name": "stage_list.3.block_list.2.se_fc1.weight",
          "mean": 0.015520600602030754,
          "std": 0.03423955664038658
        },
        {
          "name": "stage_list.3.block_list.2.se_fc1.bias",
          "mean": -0.0059403968043625355,
          "std": 0.03199540823698044
        },
        {
          "name": "stage_list.3.block_list.2.se_fc2.weight",
          "mean": 0.00368421315215528,
          "std": 0.05905961990356445
        },
        {
          "name": "stage_list.3.block_list.2.se_fc2.bias",
          "mean": -0.0832294300198555,
          "std": 0.11620660871267319
        },
        {
          "name": "stage_list.4.block_list.0.bn1.weight",
          "mean": 1.0,
          "std": 0.0
        },
        {
          "name": "stage_list.4.block_list.0.bn1.bias",
          "mean": 0.0,
          "std": 0.0
        },
        {
          "name": "stage_list.4.block_list.0.bn1.running_mean",
          "mean": 0.0,
          "std": 0.0
        },
        {
          "name": "stage_list.4.block_list.0.bn1.running_var",
          "mean": 1.0,
          "std": 0.0
        },
        {
          "name": "stage_list.4.block_list.0.conv1.conv.weight",
          "mean": 0.0003520245081745088,
          "std": 0.07948493957519531
        },
        {
          "name": "stage_list.4.block_list.0.conv1.conv.bias",
          "mean": -0.0437379851937294,
          "std": 0.05063977837562561
        },
        {
          "name": "stage_list.4.block_list.0.bn2.weight",
          "mean": 1.0,
          "std": 0.0
        },
        {
          "name": "stage_list.4.block_list.0.bn2.bias",
          "mean": 0.0,
          "std": 0.0
        },
        {
          "name": "stage_list.4.block_list.0.bn2.running_mean",
          "mean": 0.0,
          "std": 0.0
        },
        {
          "name": "stage_list.4.block_list.0.bn2.running_var",
          "mean": 1.0,
          "std": 0.0
        },
        {
          "name": "stage_list.4.block_list.0.conv2.conv.weight",
          "mean": -0.001847042003646493,
          "std": 0.07888244837522507
        },
        {
          "name": "stage_list.4.block_list.0.conv2.conv.bias",
          "mean": -0.0428563691675663,
          "std": 0.03778238594532013
        },
        {
          "name": "stage_list.4.block_list.0.bn3.weight",
          "mean": 1.0,
          "std": 0.0
        },
        {
          "name": "stage_list.4.block_list.0.bn3.bias",
          "mean": 0.0,
          "std": 0.0
        },
        {
          "name": "stage_list.4.block_list.0.bn3.running_mean",
          "mean": 0.0,
          "std": 0.0
        },
        {
          "name": "stage_list.4.block_list.0.bn3.running_var",
          "mean": 1.0,
          "std": 0.0
        },
        {
          "name": "stage_list.4.block_list.0.conv3.conv.weight",
          "mean": -0.004692289512604475,
          "std": 0.07478741556406021
        },
        {
          "name": "stage_list.4.block_list.0.conv3.conv.bias",
          "mean": -0.032844461500644684,
          "std": 0.04531945660710335
        },
        {
          "name": "stage_list.4.block_list.0.se_fc1.weight",
          "mean": 0.024225259199738503,
          "std": 0.054053522646427155
        },
        {
          "name": "stage_list.4.block_list.0.se_fc1.bias",
          "mean": -0.03860931470990181,
          "std": 0.04825550317764282
        },
        {
          "name": "stage_list.4.block_list.0.se_fc2.weight",
          "mean": 0.035987284034490585,
          "std": 0.07714254409074783
        },
        {
          "name": "stage_list.4.block_list.0.se_fc2.bias",
          "mean": -0.09634575247764587,
          "std": 0.07295447587966919
        },
        {
          "name": "stage_list.4.block_list.1.bn1.weight",
          "mean": 1.0,
          "std": 0.0
        },
        {
          "name": "stage_list.4.block_list.1.bn1.bias",
          "mean": 0.0,
          "std": 0.0
        },
        {
          "name": "stage_list.4.block_list.1.bn1.running_mean",
          "mean": 0.0,
          "std": 0.0
        },
        {
          "name": "stage_list.4.block_list.1.bn1.running_var",
          "mean": 1.0,
          "std": 0.0
        },
        {
          "name": "stage_list.4.block_list.1.conv1.conv.weight",
          "mean": -0.002629638649523258,
          "std": 0.08296302706003189
        },
        {
          "name": "stage_list.4.block_list.1.conv1.conv.bias",
          "mean": -0.044870685786008835,
          "std": 0.04377216100692749
        },
        {
          "name": "stage_list.4.block_list.1.bn2.weight",
          "mean": 1.0,
          "std": 0.0
        },
        {
          "name": "stage_list.4.block_list.1.bn2.bias",
          "mean": 0.0,
          "std": 0.0
        },
        {
          "name": "stage_list.4.block_list.1.bn2.running_mean",
          "mean": 0.0,
          "std": 0.0
        },
        {
          "name": "stage_list.4.block_list.1.bn2.running_var",
          "mean": 1.0,
          "std": 0.0
        },
        {
          "name": "stage_list.4.block_list.1.conv2.conv.weight",
          "mean": -0.0056410860270261765,
          "std": 0.07726641744375229
        },
        {
          "name": "stage_list.4.block_list.1.conv2.conv.bias",
          "mean": -0.03742368146777153,
          "std": 0.03989987447857857
        },
        {
          "name": "stage_list.4.block_list.1.bn3.weight",
          "mean": 1.0,
          "std": 0.0
        },
        {
          "name": "stage_list.4.block_list.1.bn3.bias",
          "mean": 0.0,
          "std": 0.0
        },
        {
          "name": "stage_list.4.block_list.1.bn3.running_mean",
          "mean": 0.0,
          "std": 0.0
        },
        {
          "name": "stage_list.4.block_list.1.bn3.running_var",
          "mean": 1.0,
          "std": 0.0
        },
        {
          "name": "stage_list.4.block_list.1.conv3.conv.weight",
          "mean": -0.0033114785328507423,
          "std": 0.07039815932512283
        },
        {
          "name": "stage_list.4.block_list.1.conv3.conv.bias",
          "mean": -0.02898450195789337,
          "std": 0.04311579838395119
        },
        {
          "name": "stage_list.4.block_list.1.se_fc1.weight",
          "mean": 0.035453904420137405,
          "std": 0.06349607557058334
        },
        {
          "name": "stage_list.4.block_list.1.se_fc1.bias",
          "mean": -0.07395345717668533,
          "std": 0.06660401076078415
        },
        {
          "name": "stage_list.4.block_list.1.se_fc2.weight",
          "mean": 0.014969656243920326,
          "std": 0.0805695503950119
        },
        {
          "name": "stage_list.4.block_list.1.se_fc2.bias",
          "mean": -0.07675746083259583,
          "std": 0.06856981664896011
        },
        {
          "name": "stage_list.4.block_list.2.bn1.weight",
          "mean": 1.0,
          "std": 0.0
        },
        {
          "name": "stage_list.4.block_list.2.bn1.bias",
          "mean": 0.0,
          "std": 0.0
        },
        {
          "name": "stage_list.4.block_list.2.bn1.running_mean",
          "mean": 0.0,
          "std": 0.0
        },
        {
          "name": "stage_list.4.block_list.2.bn1.running_var",
          "mean": 1.0,
          "std": 0.0
        },
        {
          "name": "stage_list.4.block_list.2.conv1.conv.weight",
          "mean": -0.00029430881841108203,
          "std": 0.08526525646448135
        },
        {
          "name": "stage_list.4.block_list.2.conv1.conv.bias",
          "mean": -0.04467032477259636,
          "std": 0.041192229837179184
        },
        {
          "name": "stage_list.4.block_list.2.bn2.weight",
          "mean": 1.0,
          "std": 0.0
        },
        {
          "name": "stage_list.4.block_list.2.bn2.bias",
          "mean": 0.0,
          "std": 0.0
        },
        {
          "name": "stage_list.4.block_list.2.bn2.running_mean",
          "mean": 0.0,
          "std": 0.0
        },
        {
          "name": "stage_list.4.block_list.2.bn2.running_var",
          "mean": 1.0,
          "std": 0.0
        },
        {
          "name": "stage_list.4.block_list.2.conv2.conv.weight",
          "mean": -0.0024228859692811966,
          "std": 0.07683724164962769
        },
        {
          "name": "stage_list.4.block_list.2.conv2.conv.bias",
          "mean": -0.048367273062467575,
          "std": 0.03397432714700699
        },
        {
          "name": "stage_list.4.block_list.2.bn3.weight",
          "mean": 1.0,
          "std": 0.0
        },
        {
          "name": "stage_list.4.block_list.2.bn3.bias",
          "mean": 0.0,
          "std": 0.0
        },
        {
          "name": "stage_list.4.block_list.2.bn3.running_mean",
          "mean": 0.0,
          "std": 0.0
        },
        {
          "name": "stage_list.4.block_list.2.bn3.running_var",
          "mean": 1.0,
          "std": 0.0
        },
        {
          "name": "stage_list.4.block_list.2.conv3.conv.weight",
          "mean": -0.003933414816856384,
          "std": 0.0727161094546318
        },
        {
          "name": "stage_list.4.block_list.2.conv3.conv.bias",
          "mean": -0.022507209330797195,
          "std": 0.05027046799659729
        },
        {
          "name": "stage_list.4.block_list.2.se_fc1.weight",
          "mean": 0.025414764881134033,
          "std": 0.06649741530418396
        },
        {
          "name": "stage_list.4.block_list.2.se_fc1.bias",
          "mean": -0.04818691313266754,
          "std": 0.05199712514877319
        },
        {
          "name": "stage_list.4.block_list.2.se_fc2.weight",
          "mean": 0.014365974813699722,
          "std": 0.08230627328157425
        },
        {
          "name": "stage_list.4.block_list.2.se_fc2.bias",
          "mean": -0.0817645862698555,
          "std": 0.06736330687999725
        },
        {
          "name": "stage_list.5.block_list.0.bn1.weight",
          "mean": 1.0,
          "std": 0.0
        },
        {
          "name": "stage_list.5.block_list.0.bn1.bias",
          "mean": 0.0,
          "std": 0.0
        },
        {
          "name": "stage_list.5.block_list.0.bn1.running_mean",
          "mean": 0.0,
          "std": 0.0
        },
        {
          "name": "stage_list.5.block_list.0.bn1.running_var",
          "mean": 1.0,
          "std": 0.0
        },
        {
          "name": "stage_list.5.block_list.0.conv1.conv.weight",
          "mean": -0.0016802826430648565,
          "std": 0.07316526770591736
        },
        {
          "name": "stage_list.5.block_list.0.conv1.conv.bias",
          "mean": -0.03766993433237076,
          "std": 0.03642380237579346
        },
        {
          "name": "stage_list.5.block_list.0.bn2.weight",
          "mean": 1.0,
          "std": 0.0
        },
        {
          "name": "stage_list.5.block_list.0.bn2.bias",
          "mean": 0.0,
          "std": 0.0
        },
        {
          "name": "stage_list.5.block_list.0.bn2.running_mean",
          "mean": 0.0,
          "std": 0.0
        },
        {
          "name": "stage_list.5.block_list.0.bn2.running_var",
          "mean": 1.0,
          "std": 0.0
        },
        {
          "name": "stage_list.5.block_list.0.conv2.conv.weight",
          "mean": -0.0007719544810242951,
          "std": 0.06283563375473022
        },
        {
          "name": "stage_list.5.block_list.0.conv2.conv.bias",
          "mean": -0.03565668314695358,
          "std": 0.02616567350924015
        },
        {
          "name": "stage_list.5.block_list.0.bn3.weight",
          "mean": 1.0,
          "std": 0.0
        },
        {
          "name": "stage_list.5.block_list.0.bn3.bias",
          "mean": 0.0,
          "std": 0.0
        },
        {
          "name": "stage_list.5.block_list.0.bn3.running_mean",
          "mean": 0.0,
          "std": 0.0
        },
        {
          "name": "stage_list.5.block_list.0.bn3.running_var",
          "mean": 1.0,
          "std": 0.0
        },
        {
          "name": "stage_list.5.block_list.0.conv3.conv.weight",
          "mean": -0.0009114335989579558,
          "std": 0.06348568946123123
        },
        {
          "name": "stage_list.5.block_list.0.conv3.conv.bias",
          "mean": -0.042237237095832825,
          "std": 0.052025459706783295
        },
        {
          "name": "stage_list.5.block_list.0.se_fc1.weight",
          "mean": 0.02295878157019615,
          "std": 0.06068338453769684
        },
        {
          "name": "stage_list.5.block_list.0.se_fc1.bias",
          "mean": -0.10284171998500824,
          "std": 0.05206675082445145
        },
        {
          "name": "stage_list.5.block_list.0.se_fc2.weight",
          "mean": 0.005190675612539053,
          "std": 0.07567068189382553
        },
        {
          "name": "stage_list.5.block_list.0.se_fc2.bias",
          "mean": -0.08424979448318481,
          "std": 0.058180246502161026
        },
        {
          "name": "stage_list.5.block_list.1.bn1.weight",
          "mean": 1.0,
          "std": 0.0
        },
        {
          "name": "stage_list.5.block_list.1.bn1.bias",
          "mean": 0.0,
          "std": 0.0
        },
        {
          "name": "stage_list.5.block_list.1.bn1.running_mean",
          "mean": 0.0,
          "std": 0.0
        },
        {
          "name": "stage_list.5.block_list.1.bn1.running_var",
          "mean": 1.0,
          "std": 0.0
        },
        {
          "name": "stage_list.5.block_list.1.conv1.conv.weight",
          "mean": -0.005080740433186293,
          "std": 0.06300359219312668
        },
        {
          "name": "stage_list.5.block_list.1.conv1.conv.bias",
          "mean": -0.02165825478732586,
          "std": 0.03197432681918144
        },
        {
          "name": "stage_list.5.block_list.1.bn2.weight",
          "mean": 1.0,
          "std": 0.0
        },
        {
          "name": "stage_list.5.block_list.1.bn2.bias",
          "mean": 0.0,
          "std": 0.0
        },
        {
          "name": "stage_list.5.block_list.1.bn2.running_mean",
          "mean": 0.0,
          "std": 0.0
        },
        {
          "name": "stage_list.5.block_list.1.bn2.running_var",
          "mean": 1.0,
          "std": 0.0
        },
        {
          "name": "stage_list.5.block_list.1.conv2.conv.weight",
          "mean": -0.0006374067743308842,
          "std": 0.059332285076379776
        },
        {
          "name": "stage_list.5.block_list.1.conv2.conv.bias",
          "mean": -0.032992616295814514,
          "std": 0.025860512629151344
        },
        {
          "name": "stage_list.5.block_list.1.bn3.weight",
          "mean": 1.0,
          "std": 0.0
        },
        {
          "name": "stage_list.5.block_list.1.bn3.bias",
          "mean": 0.0,
          "std": 0.0
        },
        {
          "name": "stage_list.5.block_list.1.bn3.running_mean",
          "mean": 0.0,
          "std": 0.0
        },
        {
          "name": "stage_list.5.block_list.1.bn3.running_var",
          "mean": 1.0,
          "std": 0.0
        },
        {
          "name": "stage_list.5.block_list.1.conv3.conv.weight",
          "mean": -0.0002411690802546218,
          "std": 0.05447401851415634
        },
        {
          "name": "stage_list.5.block_list.1.conv3.conv.bias",
          "mean": -0.04133107513189316,
          "std": 0.06317629665136337
        },
        {
          "name": "stage_list.5.block_list.1.se_fc1.weight",
          "mean": 0.014326512813568115,
          "std": 0.05870503559708595
        },
        {
          "name": "stage_list.5.block_list.1.se_fc1.bias",
          "mean": -0.12579505145549774,
          "std": 0.08866596221923828
        },
        {
          "name": "stage_list.5.block_list.1.se_fc2.weight",
          "mean": -0.001274825888685882,
          "std": 0.06806614249944687
        },
        {
          "name": "stage_list.5.block_list.1.se_fc2.bias",
          "mean": -0.0668959990143776,
          "std": 0.047709621489048004
        },
        {
          "name": "stage_list.5.block_list.2.bn1.weight",
          "mean": 1.0,
          "std": 0.0
        },
        {
          "name": "stage_list.5.block_list.2.bn1.bias",
          "mean": 0.0,
          "std": 0.0
        },
        {
          "name": "stage_list.5.block_list.2.bn1.running_mean",
          "mean": 0.0,
          "std": 0.0
        },
        {
          "name": "stage_list.5.block_list.2.bn1.running_var",
          "mean": 1.0,
          "std": 0.0
        },
        {
          "name": "stage_list.5.block_list.2.conv1.conv.weight",
          "mean": -0.005607636179775,
          "std": 0.06563886255025864
        },
        {
          "name": "stage_list.5.block_list.2.conv1.conv.bias",
          "mean": -0.0264932569116354,
          "std": 0.03434891626238823
        },
        {
          "name": "stage_list.5.block_list.2.bn2.weight",
          "mean": 1.0,
          "std": 0.0
        },
        {
          "name": "stage_list.5.block_list.2.bn2.bias",
          "mean": 0.0,
          "std": 0.0
        },
        {
          "name": "stage_list.5.block_list.2.bn2.running_mean",
          "mean": 0.0,
          "std": 0.0
        },
        {
          "name": "stage_list.5.block_list.2.bn2.running_var",
          "mean": 1.0,
          "std": 0.0
        },
        {
          "name": "stage_list.5.block_list.2.conv2.conv.weight",
          "mean": -0.0007733356324024498,
          "std": 0.06073019653558731
        },
        {
          "name": "stage_list.5.block_list.2.conv2.conv.bias",
          "mean": -0.03661230206489563,
          "std": 0.031087957322597504
        },
        {
          "name": "stage_list.5.block_list.2.bn3.weight",
          "mean": 1.0,
          "std": 0.0
        },
        {
          "name": "stage_list.5.block_list.2.bn3.bias",
          "mean": 0.0,
          "std": 0.0
        },
        {
          "name": "stage_list.5.block_list.2.bn3.running_mean",
          "mean": 0.0,
          "std": 0.0
        },
        {
          "name": "stage_list.5.block_list.2.bn3.running_var",
          "mean": 1.0,
          "std": 0.0
        },
        {
          "name": "stage_list.5.block_list.2.conv3.conv.weight",
          "mean": -0.0007392503321170807,
          "std": 0.056236252188682556
        },
        {
          "name": "stage_list.5.block_list.2.conv3.conv.bias",
          "mean": -0.04240875691175461,
          "std": 0.05710301175713539
        },
        {
          "name": "stage_list.5.block_list.2.se_fc1.weight",
          "mean": 0.01520666666328907,
          "std": 0.06063937023282051
        },
        {
          "name": "stage_list.5.block_list.2.se_fc1.bias",
          "mean": -0.09939874708652496,
          "std": 0.10040435194969177
        },
        {
          "name": "stage_list.5.block_list.2.se_fc2.weight",
          "mean": -0.0010890739504247904,
          "std": 0.07130307704210281
        },
        {
          "name": "stage_list.5.block_list.2.se_fc2.bias",
          "mean": -0.07964199036359787,
          "std": 0.04690736532211304
        },
        {
          "name": "stage_list.5.block_list.3.bn1.weight",
          "mean": 1.0,
          "std": 0.0
        },
        {
          "name": "stage_list.5.block_list.3.bn1.bias",
          "mean": 0.0,
          "std": 0.0
        },
        {
          "name": "stage_list.5.block_list.3.bn1.running_mean",
          "mean": 0.0,
          "std": 0.0
        },
        {
          "name": "stage_list.5.block_list.3.bn1.running_var",
          "mean": 1.0,
          "std": 0.0
        },
        {
          "name": "stage_list.5.block_list.3.conv1.conv.weight",
          "mean": -0.0054560317657887936,
          "std": 0.07026882469654083
        },
        {
          "name": "stage_list.5.block_list.3.conv1.conv.bias",
          "mean": -0.028422949835658073,
          "std": 0.03558429330587387
        },
        {
          "name": "stage_list.5.block_list.3.bn2.weight",
          "mean": 1.0,
          "std": 0.0
        },
        {
          "name": "stage_list.5.block_list.3.bn2.bias",
          "mean": 0.0,
          "std": 0.0
        },
        {
          "name": "stage_list.5.block_list.3.bn2.running_mean",
          "mean": 0.0,
          "std": 0.0
        },
        {
          "name": "stage_list.5.block_list.3.bn2.running_var",
          "mean": 1.0,
          "std": 0.0
        },
        {
          "name": "stage_list.5.block_list.3.conv2.conv.weight",
          "mean": -0.0022457698360085487,
          "std": 0.06215165928006172
        },
        {
          "name": "stage_list.5.block_list.3.conv2.conv.bias",
          "mean": -0.030063048005104065,
          "std": 0.028996508568525314
        },
        {
          "name": "stage_list.5.block_list.3.bn3.weight",
          "mean": 1.0,
          "std": 0.0
        },
        {
          "name": "stage_list.5.block_list.3.bn3.bias",
          "mean": 0.0,
          "std": 0.0
        },
        {
          "name": "stage_list.5.block_list.3.bn3.running_mean",
          "mean": 0.0,
          "std": 0.0
        },
        {
          "name": "stage_list.5.block_list.3.bn3.running_var",
          "mean": 1.0,
          "std": 0.0
        },
        {
          "name": "stage_list.5.block_list.3.conv3.conv.weight",
          "mean": -0.0007224519504234195,
          "std": 0.05679721012711525
        },
        {
          "name": "stage_list.5.block_list.3.conv3.conv.bias",
          "mean": -0.028265606611967087,
          "std": 0.037808794528245926
        },
        {
          "name": "stage_list.5.block_list.3.se_fc1.weight",
          "mean": 0.020107842981815338,
          "std": 0.05802243575453758
        },
        {
          "name": "stage_list.5.block_list.3.se_fc1.bias",
          "mean": -0.09400567412376404,
          "std": 0.06689523905515671
        },
        {
          "name": "stage_list.5.block_list.3.se_fc2.weight",
          "mean": -0.008319023996591568,
          "std": 0.07146201282739639
        },
        {
          "name": "stage_list.5.block_list.3.se_fc2.bias",
          "mean": -0.051506925374269485,
          "std": 0.06265554577112198
        },
        {
          "name": "stage_list.6.block_list.0.bn1.weight",
          "mean": 1.0,
          "std": 0.0
        },
        {
          "name": "stage_list.6.block_list.0.bn1.bias",
          "mean": 0.0,
          "std": 0.0
        },
        {
          "name": "stage_list.6.block_list.0.bn1.running_mean",
          "mean": 0.0,
          "std": 0.0
        },
        {
          "name": "stage_list.6.block_list.0.bn1.running_var",
          "mean": 1.0,
          "std": 0.0
        },
        {
          "name": "stage_list.6.block_list.0.conv1.conv.weight",
          "mean": -0.006548270117491484,
          "std": 0.07346604764461517
        },
        {
          "name": "stage_list.6.block_list.0.conv1.conv.bias",
          "mean": -0.03225092962384224,
          "std": 0.0390000194311142
        },
        {
          "name": "stage_list.6.block_list.0.bn2.weight",
          "mean": 1.0,
          "std": 0.0
        },
        {
          "name": "stage_list.6.block_list.0.bn2.bias",
          "mean": 0.0,
          "std": 0.0
        },
        {
          "name": "stage_list.6.block_list.0.bn2.running_mean",
          "mean": 0.0,
          "std": 0.0
        },
        {
          "name": "stage_list.6.block_list.0.bn2.running_var",
          "mean": 1.0,
          "std": 0.0
        },
        {
          "name": "stage_list.6.block_list.0.conv2.conv.weight",
          "mean": -0.0007709972560405731,
          "std": 0.05897851288318634
        },
        {
          "name": "stage_list.6.block_list.0.conv2.conv.bias",
          "mean": -0.044856466352939606,
          "std": 0.0351494662463665
        },
        {
          "name": "stage_list.6.block_list.0.bn3.weight",
          "mean": 1.0,
          "std": 0.0
        },
        {
          "name": "stage_list.6.block_list.0.bn3.bias",
          "mean": 0.0,
          "std": 0.0
        },
        {
          "name": "stage_list.6.block_list.0.bn3.running_mean",
          "mean": 0.0,
          "std": 0.0
        },
        {
          "name": "stage_list.6.block_list.0.bn3.running_var",
          "mean": 1.0,
          "std": 0.0
        },
        {
          "name": "stage_list.6.block_list.0.conv3.conv.weight",
          "mean": 3.5974753700429574e-05,
          "std": 0.05938481166958809
        },
        {
          "name": "stage_list.6.block_list.0.conv3.conv.bias",
          "mean": -0.013813687488436699,
          "std": 0.06589851528406143
        },
        {
          "name": "stage_list.6.block_list.0.se_fc1.weight",
          "mean": 0.006925972178578377,
          "std": 0.061632685363292694
        },
        {
          "name": "stage_list.6.block_list.0.se_fc1.bias",
          "mean": -0.12418648600578308,
          "std": 0.10522086918354034
        },
        {
          "name": "stage_list.6.block_list.0.se_fc2.weight",
          "mean": -0.001980121247470379,
          "std": 0.0768924281001091
        },
        {
          "name": "stage_list.6.block_list.0.se_fc2.bias",
          "mean": -0.07635967433452606,
          "std": 0.06251411885023117
        },
        {
          "name": "stage_list.6.block_list.1.bn1.weight",
          "mean": 1.0,
          "std": 0.0
        },
        {
          "name": "stage_list.6.block_list.1.bn1.bias",
          "mean": 0.0,
          "std": 0.0
        },
        {
          "name": "stage_list.6.block_list.1.bn1.running_mean",
          "mean": 0.0,
          "std": 0.0
        },
        {
          "name": "stage_list.6.block_list.1.bn1.running_var",
          "mean": 1.0,
          "std": 0.0
        },
        {
          "name": "stage_list.6.block_list.1.conv1.conv.weight",
          "mean": -0.02717195823788643,
          "std": 0.07033412158489227
        },
        {
          "name": "stage_list.6.block_list.1.conv1.conv.bias",
          "mean": -0.08949248492717743,
          "std": 0.056745003908872604
        },
        {
          "name": "stage_list.6.block_list.1.bn2.weight",
          "mean": 1.0,
          "std": 0.0
        },
        {
          "name": "stage_list.6.block_list.1.bn2.bias",
          "mean": 0.0,
          "std": 0.0
        },
        {
          "name": "stage_list.6.block_list.1.bn2.running_mean",
          "mean": 0.0,
          "std": 0.0
        },
        {
          "name": "stage_list.6.block_list.1.bn2.running_var",
          "mean": 1.0,
          "std": 0.0
        },
        {
          "name": "stage_list.6.block_list.1.conv2.conv.weight",
          "mean": -0.0002831969759427011,
          "std": 0.05535650998353958
        },
        {
          "name": "stage_list.6.block_list.1.conv2.conv.bias",
          "mean": -0.025571541860699654,
          "std": 0.03714310750365257
        },
        {
          "name": "stage_list.6.block_list.1.bn3.weight",
          "mean": 1.0,
          "std": 0.0
        },
        {
          "name": "stage_list.6.block_list.1.bn3.bias",
          "mean": 0.0,
          "std": 0.0
        },
        {
          "name": "stage_list.6.block_list.1.bn3.running_mean",
          "mean": 0.0,
          "std": 0.0
        },
        {
          "name": "stage_list.6.block_list.1.bn3.running_var",
          "mean": 1.0,
          "std": 0.0
        },
        {
          "name": "stage_list.6.block_list.1.conv3.conv.weight",
          "mean": 0.0005289469845592976,
          "std": 0.0638754665851593
        },
        {
          "name": "stage_list.6.block_list.1.conv3.conv.bias",
          "mean": -0.01692427694797516,
          "std": 0.06532381474971771
        },
        {
          "name": "stage_list.6.block_list.1.se_fc1.weight",
          "mean": 0.006998445838689804,
          "std": 0.07678666710853577
        },
        {
          "name": "stage_list.6.block_list.1.se_fc1.bias",
          "mean": -0.15175266563892365,
          "std": 0.09291450679302216
        },
        {
          "name": "stage_list.6.block_list.1.se_fc2.weight",
          "mean": -0.01559760794043541,
          "std": 0.08480352908372879
        },
        {
          "name": "stage_list.6.block_list.1.se_fc2.bias",
          "mean": -0.06415139883756638,
          "std": 0.06371770799160004
        },
        {
          "name": "stage_list.6.block_list.2.bn1.weight",
          "mean": 1.0,
          "std": 0.0
        },
        {
          "name": "stage_list.6.block_list.2.bn1.bias",
          "mean": 0.0,
          "std": 0.0
        },
        {
          "name": "stage_list.6.block_list.2.bn1.running_mean",
          "mean": 0.0,
          "std": 0.0
        },
        {
          "name": "stage_list.6.block_list.2.bn1.running_var",
          "mean": 1.0,
          "std": 0.0
        },
        {
          "name": "stage_list.6.block_list.2.conv1.conv.weight",
          "mean": -0.028640467673540115,
          "std": 0.06987634301185608
        },
        {
          "name": "stage_list.6.block_list.2.conv1.conv.bias",
          "mean": -0.09340719878673553,
          "std": 0.05050213262438774
        },
        {
          "name": "stage_list.6.block_list.2.bn2.weight",
          "mean": 1.0,
          "std": 0.0
        },
        {
          "name": "stage_list.6.block_list.2.bn2.bias",
          "mean": 0.0,
          "std": 0.0
        },
        {
          "name": "stage_list.6.block_list.2.bn2.running_mean",
          "mean": 0.0,
          "std": 0.0
        },
        {
          "name": "stage_list.6.block_list.2.bn2.running_var",
          "mean": 1.0,
          "std": 0.0
        },
        {
          "name": "stage_list.6.block_list.2.conv2.conv.weight",
          "mean": 9.711258462630212e-05,
          "std": 0.05313882604241371
        },
        {
          "name": "stage_list.6.block_list.2.conv2.conv.bias",
          "mean": -0.023330051451921463,
          "std": 0.036943286657333374
        },
        {
          "name": "stage_list.6.block_list.2.bn3.weight",
          "mean": 1.0,
          "std": 0.0
        },
        {
          "name": "stage_list.6.block_list.2.bn3.bias",
          "mean": 0.0,
          "std": 0.0
        },
        {
          "name": "stage_list.6.block_list.2.bn3.running_mean",
          "mean": 0.0,
          "std": 0.0
        },
        {
          "name": "stage_list.6.block_list.2.bn3.running_var",
          "mean": 1.0,
          "std": 0.0
        },
        {
          "name": "stage_list.6.block_list.2.conv3.conv.weight",
          "mean": 0.0005254546995274723,
          "std": 0.06276802718639374
        },
        {
          "name": "stage_list.6.block_list.2.conv3.conv.bias",
          "mean": -0.013006485998630524,
          "std": 0.056962840259075165
        },
        {
          "name": "stage_list.6.block_list.2.se_fc1.weight",
          "mean": 0.005457879975438118,
          "std": 0.07519695907831192
        },
        {
          "name": "stage_list.6.block_list.2.se_fc1.bias",
          "mean": -0.1255628913640976,
          "std": 0.10447492450475693
        },
        {
          "name": "stage_list.6.block_list.2.se_fc2.weight",
          "mean": -0.011858259327709675,
          "std": 0.08485457301139832
        },
        {
          "name": "stage_list.6.block_list.2.se_fc2.bias",
          "mean": -0.06806787848472595,
          "std": 0.06727142632007599
        },
        {
          "name": "stage_list.6.block_list.3.bn1.weight",
          "mean": 1.0,
          "std": 0.0
        },
        {
          "name": "stage_list.6.block_list.3.bn1.bias",
          "mean": 0.0,
          "std": 0.0
        },
        {
          "name": "stage_list.6.block_list.3.bn1.running_mean",
          "mean": 0.0,
          "std": 0.0
        },
        {
          "name": "stage_list.6.block_list.3.bn1.running_var",
          "mean": 1.0,
          "std": 0.0
        },
        {
          "name": "stage_list.6.block_list.3.conv1.conv.weight",
          "mean": -0.024497251957654953,
          "std": 0.07065949589014053
        },
        {
          "name": "stage_list.6.block_list.3.conv1.conv.bias",
          "mean": -0.08515985310077667,
          "std": 0.04179651290178299
        },
        {
          "name": "stage_list.6.block_list.3.bn2.weight",
          "mean": 1.0,
          "std": 0.0
        },
        {
          "name": "stage_list.6.block_list.3.bn2.bias",
          "mean": 0.0,
          "std": 0.0
        },
        {
          "name": "stage_list.6.block_list.3.bn2.running_mean",
          "mean": 0.0,
          "std": 0.0
        },
        {
          "name": "stage_list.6.block_list.3.bn2.running_var",
          "mean": 1.0,
          "std": 0.0
        },
        {
          "name": "stage_list.6.block_list.3.conv2.conv.weight",
          "mean": 0.0008080482366494834,
          "std": 0.047915685921907425
        },
        {
          "name": "stage_list.6.block_list.3.conv2.conv.bias",
          "mean": -0.016869286075234413,
          "std": 0.037063874304294586
        },
        {
          "name": "stage_list.6.block_list.3.bn3.weight",
          "mean": 1.0,
          "std": 0.0
        },
        {
          "name": "stage_list.6.block_list.3.bn3.bias",
          "mean": 0.0,
          "std": 0.0
        },
        {
          "name": "stage_list.6.block_list.3.bn3.running_mean",
          "mean": 0.0,
          "std": 0.0
        },
        {
          "name": "stage_list.6.block_list.3.bn3.running_var",
          "mean": 1.0,
          "std": 0.0
        },
        {
          "name": "stage_list.6.block_list.3.conv3.conv.weight",
          "mean": 0.0003347851161379367,
          "std": 0.05658004805445671
        },
        {
          "name": "stage_list.6.block_list.3.conv3.conv.bias",
          "mean": -0.009404076263308525,
          "std": 0.05907965824007988
        },
        {
          "name": "stage_list.6.block_list.3.se_fc1.weight",
          "mean": 0.0008570537902414799,
          "std": 0.06609617173671722
        },
        {
          "name": "stage_list.6.block_list.3.se_fc1.bias",
          "mean": -0.11341439932584763,
          "std": 0.1207091435790062
        },
        {
          "name": "stage_list.6.block_list.3.se_fc2.weight",
          "mean": -0.0012384883593767881,
          "std": 0.07709804177284241
        },
        {
          "name": "stage_list.6.block_list.3.se_fc2.bias",
          "mean": -0.08390437811613083,
          "std": 0.0618237666785717
        },
        {
          "name": "dense.weight",
          "mean": -0.00011800534412031993,
          "std": 0.029579682275652885
        },
        {
          "name": "dense.bias",
          "mean": -0.003952397499233484,
          "std": 0.02606271766126156
        }
      ]
    }
  ]
}